blend2bam/__init__.py
blend2bam/__main__.py
blend2bam/blend2gltf.py
blend2bam/blenderutils.py
blend2bam/cli.py
blend2bam/common.py
blend2bam/gltf2bam.py
blend2bam/loader.py
blend2bam/version.py
blend2bam/blender_scripts/exportgltf.py
panda3d_blend2bam-0.25.0.dist-info/LICENSE.txt
panda3d_blend2bam-0.25.0.dist-info/METADATA
panda3d_blend2bam-0.25.0.dist-info/WHEEL
panda3d_blend2bam-0.25.0.dist-info/entry_points.txt
panda3d_blend2bam-0.25.0.dist-info/top_level.txt
panda3d_blend2bam-0.25.0.dist-info/RECORD
