Metadata-Version: 2.1
Name: panda3d-blend2bam
Version: 0.25.0
Summary: A tool to convert Blender blend files to Panda3D BAM files
Author: Mitchell Stokes
License: MIT
Project-URL: homepage, https://github.com/Moguri/blend2bam
Keywords: panda3d,gamedev
Classifier: Development Status :: 4 - Beta
Classifier: License :: OSI Approved :: MIT License
Classifier: Programming Language :: Python :: 3
Requires-Python: >=3.8
License-File: LICENSE.txt
Requires-Dist: panda3d
Requires-Dist: panda3d-gltf ~=1.1.0
Provides-Extra: test
Requires-Dist: pytest ; extra == 'test'
Requires-Dist: pylint ~=2.4.0 ; extra == 'test'
Requires-Dist: pytest-pylint ; extra == 'test'
